sagellm_core/__init__.py
sagellm_core/__init__.pyc
sagellm_core/__main__.pyc
sagellm_core/config.pyc
sagellm_core/demo.pyc
sagellm_core/engine.pyc
sagellm_core/engine_factory.pyc
sagellm_core/engine_server.pyc
sagellm_core/factory.pyc
sagellm_core/health.pyc
sagellm_core/llm_engine.pyc
sagellm_core/pd_executor.pyc
sagellm_core/plugins.pyc
sagellm_core/py.typed
sagellm_core/runner.pyc
sagellm_core/runtime.pyc
sagellm_core/workload.pyc
sagellm_core/__pycache__/__init__.cpython-311.pyc
sagellm_core/__pycache__/base_engine.cpython-311.pyc
sagellm_core/__pycache__/config.cpython-311.pyc
sagellm_core/__pycache__/demo.cpython-311.pyc
sagellm_core/__pycache__/engine.cpython-311.pyc
sagellm_core/__pycache__/engine_factory.cpython-311.pyc
sagellm_core/__pycache__/engine_server.cpython-311.pyc
sagellm_core/__pycache__/factory.cpython-311.pyc
sagellm_core/__pycache__/health.cpython-311.pyc
sagellm_core/__pycache__/llm_engine.cpython-311.pyc
sagellm_core/__pycache__/mock_engine.cpython-311.pyc
sagellm_core/__pycache__/pd_executor.cpython-311.pyc
sagellm_core/__pycache__/plugins.cpython-311.pyc
sagellm_core/__pycache__/runner.cpython-311.pyc
sagellm_core/__pycache__/runtime.cpython-311.pyc
sagellm_core/__pycache__/workload.cpython-311.pyc
sagellm_core/decoding/__init__.py
sagellm_core/decoding/__init__.pyc
sagellm_core/decoding/base.pyc
sagellm_core/decoding/beam_search.pyc
sagellm_core/decoding/contrastive.pyc
sagellm_core/decoding/greedy.pyc
sagellm_core/decoding/sampling.pyc
sagellm_core/decoding/__pycache__/__init__.cpython-311.pyc
sagellm_core/decoding/__pycache__/base.cpython-311.pyc
sagellm_core/decoding/__pycache__/beam_search.cpython-311.pyc
sagellm_core/decoding/__pycache__/contrastive.cpython-311.pyc
sagellm_core/decoding/__pycache__/greedy.cpython-311.pyc
sagellm_core/decoding/__pycache__/sampling.cpython-311.pyc
sagellm_core/distributed/__init__.py
sagellm_core/distributed/__init__.pyc
sagellm_core/distributed/strategies.pyc
isagellm_core-0.4.0.18.dist-info/METADATA
isagellm_core-0.4.0.18.dist-info/WHEEL
isagellm_core-0.4.0.18.dist-info/entry_points.txt
isagellm_core-0.4.0.18.dist-info/top_level.txt
isagellm_core-0.4.0.18.dist-info/RECORD
