Metadata-Version: 2.4
Name: isagellm-core
Version: 0.4.0.18
Summary: sageLLM core runtime with PD separation (MVP)
Author: IntelliStream Team
License: Proprietary - IntelliStream
Classifier: Development Status :: 3 - Alpha
Classifier: Programming Language :: Python :: 3
Classifier: Programming Language :: Python :: 3.10
Classifier: Programming Language :: Python :: 3.11
Classifier: Programming Language :: Python :: 3.12
Requires-Python: ==3.11.*
Requires-Dist: pydantic>=2.0.0
Requires-Dist: pyyaml>=6.0.0
Requires-Dist: isagellm-protocol<0.5.0,>=0.4.0.0
Requires-Dist: isagellm-backend<0.5.0,>=0.4.0.0
Requires-Dist: isagellm-comm<0.5.0,>=0.4.0.0
Requires-Dist: isagellm-kv-cache<0.5.0,>=0.4.0.0
Requires-Dist: fastapi>=0.100.0
Requires-Dist: uvicorn>=0.22.0
Requires-Dist: torch>=2.0.0
Requires-Dist: transformers>=4.35.0
Requires-Dist: accelerate>=0.26.0
Provides-Extra: dev
Requires-Dist: pytest>=7.0.0; extra == "dev"
Requires-Dist: pytest-cov>=4.0.0; extra == "dev"
Requires-Dist: pytest-timeout>=2.0.0; extra == "dev"
Requires-Dist: ruff>=0.8.0; extra == "dev"
Requires-Dist: mypy>=1.0.0; extra == "dev"
Requires-Dist: types-PyYAML>=6.0.0; extra == "dev"
Requires-Dist: pre-commit>=3.0.0; extra == "dev"
Requires-Dist: isage-pypi-publisher>=0.2.0; extra == "dev"
